LICENSE
MANIFEST.in
README.rst
requirements-test.txt
requirements.txt
setup.py
bin/loopabull
examples/inventory.txt
examples/configs/ansible.cfg
examples/configs/fedmsg_example.yml
examples/configs/fedmsg_rabbitmq_example.yml
examples/configs/rkdir_example.yml
examples/playbooks/org.fedoraproject.prod.ansible.playbook.start.yml
examples/playbooks/org.fedoraproject.prod.buildsys.build.state.change.yml
loopabull/__init__.py
loopabull/main.py
loopabull/plugin.py
loopabull.egg-info/PKG-INFO
loopabull.egg-info/SOURCES.txt
loopabull.egg-info/dependency_links.txt
loopabull.egg-info/requires.txt
loopabull.egg-info/top_level.txt
loopabull/plugins/__init__.py
loopabull/plugins/fedmsglooper.py
loopabull/plugins/fedmsgrabbitmqlooper.py
loopabull/plugins/redislooper.py
loopabull/plugins/rkdirectorytranslator.py
loopabull/plugins/rknametranslator.py
man/loopabull.1
man/loopabull.txt2man
systemd/loopabull.service
systemd/loopabull.yml
systemd/sysconfig.loopabull