Metadata-Version: 1.1
Name: loopabull
Version: 0.0.7
Summary: Event loop driven Ansible playbook execution engine
Home-page: https://github.com/maxamillion/loopabull
Author: Adam Miller
Author-email: admiller@redhat.com
License: GPLv3+
Platform: UNKNOWN
Classifier: Development Status :: 3 - Alpha
Classifier: License :: OSI Approved :: GNU General Public License v3 or later (GPLv3+)
Classifier: Programming Language :: Python :: 2.7
Classifier: Programming Language :: Python :: 3
Classifier: Topic :: System :: Systems Administration
